Workbook

Sheet Cover
B2: CloudMigrate.in
B3: Post-Migration Checklist — Azure
B4: Microsoft Azure · v1.0 · generated 21 Oct 2026
B6: Purpose | C6: Validation and handover gate after each migration wave.
B7: Customer
B8: Project / programme
B9: Prepared by
B10: Reviewed by
B11: Last updated
B13: How to use | C13: 1. Copy the Checklist sheet once per wave (or filter by wave in the Wave column).
C14: 2. Assign an owner and due date to every item; set Status from the drop-down.
C15: 3. Attach evidence links in the Evidence column — auditors and funding reviewers will ask.
C16: 4. The Summary sheet calculates completion by area; go-live needs every Critical item Done or N/A.
B18: Reference | C18: Target regions: Central India (Pune), South India (Chennai), West India (Mumbai)
C19: Landing zone: Azure Landing Zones (CAF) — management groups, Azure Policy
C20: Security baseline: Microsoft Cloud Security Benchmark / CIS Microsoft Azure Foundations
B23: Template provided as-is for planning purposes. Validate vendor programme terms and service availability before relying on them.

Sheet Summary
A1: Area | B1: Items | C1: Done | D1: In progress | E1: Blocked | F1: Not started | G1: N/A | H1: % complete
A2: Functional validation | B2: =COUNTIF('Checklist'!$B:$B,A2) | C2: =COUNTIFS('Checklist'!$B:$B,$A2,'Checklist'!$H:$H,"Done") | D2: =COUNTIFS('Checklist'!$B:$B,$A2,'Checklist'!$H:$H,"In progress") | E2: =COUNTIFS('Checklist'!$B:$B,$A2,'Checklist'!$H:$H,"Blocked") | F2: =COUNTIFS('Checklist'!$B:$B,$A2,'Checklist'!$H:$H,"Not started") | G2: =COUNTIFS('Checklist'!$B:$B,$A2,'Checklist'!$H:$H,"N/A") | H2: =IFERROR(C2/(B2-G2),0)
A3: Performance | B3: =COUNTIF('Checklist'!$B:$B,A3) | C3: =COUNTIFS('Checklist'!$B:$B,$A3,'Checklist'!$H:$H,"Done") | D3: =COUNTIFS('Checklist'!$B:$B,$A3,'Checklist'!$H:$H,"In progress") | E3: =COUNTIFS('Checklist'!$B:$B,$A3,'Checklist'!$H:$H,"Blocked") | F3: =COUNTIFS('Checklist'!$B:$B,$A3,'Checklist'!$H:$H,"Not started") | G3: =COUNTIFS('Checklist'!$B:$B,$A3,'Checklist'!$H:$H,"N/A") | H3: =IFERROR(C3/(B3-G3),0)
A4: Data integrity | B4: =COUNTIF('Checklist'!$B:$B,A4) | C4: =COUNTIFS('Checklist'!$B:$B,$A4,'Checklist'!$H:$H,"Done") | D4: =COUNTIFS('Checklist'!$B:$B,$A4,'Checklist'!$H:$H,"In progress") | E4: =COUNTIFS('Checklist'!$B:$B,$A4,'Checklist'!$H:$H,"Blocked") | F4: =COUNTIFS('Checklist'!$B:$B,$A4,'Checklist'!$H:$H,"Not started") | G4: =COUNTIFS('Checklist'!$B:$B,$A4,'Checklist'!$H:$H,"N/A") | H4: =IFERROR(C4/(B4-G4),0)
A5: Security | B5: =COUNTIF('Checklist'!$B:$B,A5) | C5: =COUNTIFS('Checklist'!$B:$B,$A5,'Checklist'!$H:$H,"Done") | D5: =COUNTIFS('Checklist'!$B:$B,$A5,'Checklist'!$H:$H,"In progress") | E5: =COUNTIFS('Checklist'!$B:$B,$A5,'Checklist'!$H:$H,"Blocked") | F5: =COUNTIFS('Checklist'!$B:$B,$A5,'Checklist'!$H:$H,"Not started") | G5: =COUNTIFS('Checklist'!$B:$B,$A5,'Checklist'!$H:$H,"N/A") | H5: =IFERROR(C5/(B5-G5),0)
A6: Monitoring | B6: =COUNTIF('Checklist'!$B:$B,A6) | C6: =COUNTIFS('Checklist'!$B:$B,$A6,'Checklist'!$H:$H,"Done") | D6: =COUNTIFS('Checklist'!$B:$B,$A6,'Checklist'!$H:$H,"In progress") | E6: =COUNTIFS('Checklist'!$B:$B,$A6,'Checklist'!$H:$H,"Blocked") | F6: =COUNTIFS('Checklist'!$B:$B,$A6,'Checklist'!$H:$H,"Not started") | G6: =COUNTIFS('Checklist'!$B:$B,$A6,'Checklist'!$H:$H,"N/A") | H6: =IFERROR(C6/(B6-G6),0)
A7: Backup & DR | B7: =COUNTIF('Checklist'!$B:$B,A7) | C7: =COUNTIFS('Checklist'!$B:$B,$A7,'Checklist'!$H:$H,"Done") | D7: =COUNTIFS('Checklist'!$B:$B,$A7,'Checklist'!$H:$H,"In progress") | E7: =COUNTIFS('Checklist'!$B:$B,$A7,'Checklist'!$H:$H,"Blocked") | F7: =COUNTIFS('Checklist'!$B:$B,$A7,'Checklist'!$H:$H,"Not started") | G7: =COUNTIFS('Checklist'!$B:$B,$A7,'Checklist'!$H:$H,"N/A") | H7: =IFERROR(C7/(B7-G7),0)
A8: Cost & tagging | B8: =COUNTIF('Checklist'!$B:$B,A8) | C8: =COUNTIFS('Checklist'!$B:$B,$A8,'Checklist'!$H:$H,"Done") | D8: =COUNTIFS('Checklist'!$B:$B,$A8,'Checklist'!$H:$H,"In progress") | E8: =COUNTIFS('Checklist'!$B:$B,$A8,'Checklist'!$H:$H,"Blocked") | F8: =COUNTIFS('Checklist'!$B:$B,$A8,'Checklist'!$H:$H,"Not started") | G8: =COUNTIFS('Checklist'!$B:$B,$A8,'Checklist'!$H:$H,"N/A") | H8: =IFERROR(C8/(B8-G8),0)
A9: Operations handover | B9: =COUNTIF('Checklist'!$B:$B,A9) | C9: =COUNTIFS('Checklist'!$B:$B,$A9,'Checklist'!$H:$H,"Done") | D9: =COUNTIFS('Checklist'!$B:$B,$A9,'Checklist'!$H:$H,"In progress") | E9: =COUNTIFS('Checklist'!$B:$B,$A9,'Checklist'!$H:$H,"Blocked") | F9: =COUNTIFS('Checklist'!$B:$B,$A9,'Checklist'!$H:$H,"Not started") | G9: =COUNTIFS('Checklist'!$B:$B,$A9,'Checklist'!$H:$H,"N/A") | H9: =IFERROR(C9/(B9-G9),0)
A10: Decommission | B10: =COUNTIF('Checklist'!$B:$B,A10) | C10: =COUNTIFS('Checklist'!$B:$B,$A10,'Checklist'!$H:$H,"Done") | D10: =COUNTIFS('Checklist'!$B:$B,$A10,'Checklist'!$H:$H,"In progress") | E10: =COUNTIFS('Checklist'!$B:$B,$A10,'Checklist'!$H:$H,"Blocked") | F10: =COUNTIFS('Checklist'!$B:$B,$A10,'Checklist'!$H:$H,"Not started") | G10: =COUNTIFS('Checklist'!$B:$B,$A10,'Checklist'!$H:$H,"N/A") | H10: =IFERROR(C10/(B10-G10),0)
A11: Documentation | B11: =COUNTIF('Checklist'!$B:$B,A11) | C11: =COUNTIFS('Checklist'!$B:$B,$A11,'Checklist'!$H:$H,"Done") | D11: =COUNTIFS('Checklist'!$B:$B,$A11,'Checklist'!$H:$H,"In progress") | E11: =COUNTIFS('Checklist'!$B:$B,$A11,'Checklist'!$H:$H,"Blocked") | F11: =COUNTIFS('Checklist'!$B:$B,$A11,'Checklist'!$H:$H,"Not started") | G11: =COUNTIFS('Checklist'!$B:$B,$A11,'Checklist'!$H:$H,"N/A") | H11: =IFERROR(C11/(B11-G11),0)
A12: Business sign-off | B12: =COUNTIF('Checklist'!$B:$B,A12) | C12: =COUNTIFS('Checklist'!$B:$B,$A12,'Checklist'!$H:$H,"Done") | D12: =COUNTIFS('Checklist'!$B:$B,$A12,'Checklist'!$H:$H,"In progress") | E12: =COUNTIFS('Checklist'!$B:$B,$A12,'Checklist'!$H:$H,"Blocked") | F12: =COUNTIFS('Checklist'!$B:$B,$A12,'Checklist'!$H:$H,"Not started") | G12: =COUNTIFS('Checklist'!$B:$B,$A12,'Checklist'!$H:$H,"N/A") | H12: =IFERROR(C12/(B12-G12),0)
A13: Total | B13: =SUM(B2:B12) | C13: =SUM(C2:C12) | D13: =SUM(D2:D12) | E13: =SUM(E2:E12) | F13: =SUM(F2:F12) | G13: =SUM(G2:G12) | H13: =IFERROR(C13/(B13-G13),0)
A15: Go-live readiness rule: all Critical items Done or N/A, no Blocked items, ≥ 90% overall.
A16: Critical items not yet Done | B16: =COUNTIFS('Checklist'!$G:$G,"Critical",'Checklist'!$H:$H,"<>Done",'Checklist'!$H:$H,"<>N/A",'Checklist'!$A:$A,"<>ID")

Sheet Checklist
A1: ID | B1: Area | C1: Item | D1: Guidance | E1: Azure tool / reference | F1: Owner | G1: Priority | H1: Status | I1: Due date | J1: Wave | K1: Evidence / notes
A2: POST-001 | B2: Functional validation | C2: Application smoke tests passed | D2: Log-in, key transactions, reports, integrations. | E2: UAT scripts | G2: Critical | H2: Not started
A3: POST-002 | B3: Functional validation | C3: End-to-end business process tested by the owner | D3: Owner signs the result, not the project team. | E3: UAT sign-off | G3: Critical | H3: Not started
A4: POST-003 | B4: Functional validation | C4: Integrations and interfaces confirmed (inbound and outbound) | D4: Payment gateways, SaaS, partners, file drops. | E4: Integration register | G4: Critical | H4: Not started
A5: POST-004 | B5: Functional validation | C5: Batch jobs ran successfully on schedule | D5: Compare runtime with the source baseline. | E5: Scheduler logs | G5: High | H5: Not started
A6: POST-005 | B6: Functional validation | C6: Email / SMTP relay, printing and file shares working | D6: Often forgotten until Monday morning. | E6: Smoke tests | G6: Medium | H6: Not started
A7: POST-006 | B7: Performance | C7: Key transaction response times within baseline tolerance | D7: Typical tolerance ± 10%. | E7: Azure Monitor, Log Analytics, Application Insights | G7: High | H7: Not started
A8: POST-007 | B8: Performance | C8: Resource utilisation reviewed after 7 days | D8: Right-size over- and under-provisioned resources. | E8: Azure Monitor, Log Analytics, Application Insights | G8: Medium | H8: Not started
A9: POST-008 | B9: Performance | C9: Database wait events / query performance reviewed | D9: Compare top SQL with the source. | E9: DB monitoring | G9: High | H9: Not started
A10: POST-009 | B10: Data integrity | C10: Row counts and checksums reconciled | D10: All tables or a signed sample for very large tables. | E10: Validation scripts | G10: Critical | H10: Not started
A11: POST-010 | B11: Data integrity | C11: Business control totals match (e.g. ledger balances) | D11: Signed by finance or the data owner. | E11: Reconciliation report | G11: Critical | H11: Not started
A12: POST-011 | B12: Data integrity | C12: Replication / CDC stopped and source set read-only | D12: Prevents split-brain writes. | E12: Azure Database Migration Service / SQL Managed Instance link | G12: Critical | H12: Not started
A13: POST-012 | B13: Security | C13: Security posture score reviewed for new resources | D13: Microsoft Defender for Cloud (Defender CSPM, Secure Score) | E13: Microsoft Cloud Security Benchmark / CIS Microsoft Azure Foundations | G13: High | H13: Not started
... A36: POST-035 | B36: Business sign-off | C36: Benefits tracker updated (cost, performance, risk) | D36: Feeds the business case review. | E36: Benefits tracker | G36: Medium | H36: Not started
